dpixiv/__init__.py
dpixiv-4.1.0.dist-info/LICENSE
dpixiv-4.1.0.dist-info/METADATA
dpixiv-4.1.0.dist-info/WHEEL
dpixiv-4.1.0.dist-info/top_level.txt
dpixiv-4.1.0.dist-info/RECORD
