Metadata-Version: 2.1
Name: dpixiv
Version: 4.1.0
Summary: Tool to simple use pixiv api of site (Python >= 3.5)
Home-page: https://github.com/dalor/dpixiv
Author: dalor
Author-email: dalor@i.ua
License: UNKNOWN
Platform: UNKNOWN
Classifier: Programming Language :: Python :: 3
Classifier: License :: OSI Approved :: MIT License
Classifier: Operating System :: OS Independent
Requires-Dist: aiohttp
